nonebot_plugin_pong/__init__.py
nonebot_plugin_pong-0.1.2.dist-info/LICENSE
nonebot_plugin_pong-0.1.2.dist-info/METADATA
nonebot_plugin_pong-0.1.2.dist-info/WHEEL
nonebot_plugin_pong-0.1.2.dist-info/RECORD
